cluster_cli/__init__.py
cluster_cli/__version__.py
cluster_cli/main.py
k3_cluster_cli-1.0.20.dist-info/licenses/LICENSE
k3_cluster_cli-1.0.20.dist-info/METADATA
k3_cluster_cli-1.0.20.dist-info/WHEEL
k3_cluster_cli-1.0.20.dist-info/entry_points.txt
k3_cluster_cli-1.0.20.dist-info/top_level.txt
k3_cluster_cli-1.0.20.dist-info/RECORD
