Metadata-Version: 2.4
Name: k3-cluster-cli
Version: 1.0.20
Summary: Minimal CLI for managing your K3s cluster
Author-email: Aleksey Lichtman <alichtman@users.noreply.github.com>
License-Expression: MIT
Project-URL: Homepage, https://gitlab.com/aleksey-lichtman/k3-cluster-cli
Project-URL: Repository, https://gitlab.com/aleksey-lichtman/k3-cluster-cli
Project-URL: Issues, https://gitlab.com/aleksey-lichtman/k3-cluster-cli/-/issues
Keywords: k3s,kubernetes,cluster,cli,raspberry-pi
Classifier: Development Status :: 4 - Beta
Classifier: Intended Audience :: System Administrators
Classifier: Operating System :: POSIX :: Linux
Classifier: Programming Language :: Python :: 3
Classifier: Programming Language :: Python :: 3.8
Classifier: Programming Language :: Python :: 3.9
Classifier: Programming Language :: Python :: 3.10
Classifier: Programming Language :: Python :: 3.11
Classifier: Programming Language :: Python :: 3.12
Classifier: Topic :: System :: Systems Administration
Requires-Python: >=3.8
License-File: LICENSE
Requires-Dist: typer>=0.9.0
Requires-Dist: requests>=2.31.0
Provides-Extra: test
Requires-Dist: pytest>=7.0.0; extra == "test"
Requires-Dist: pytest-cov>=4.0.0; extra == "test"
Dynamic: license-file
